Metadata-Version: 2.4
Name: jinja2-cli-gu
Version: 0.8.2.1
Summary: A CLI interface to Jinja2 (fork of the original)
Home-page: https://github.com/juur/jinja2-cli-gu
Author: Matt Robenolt
Author-email: matt@ydekproductions.com
Maintainer: "juur"
Maintainer-email: "juur@users.noreply.github.com"
License: BSD
Classifier: Intended Audience :: Developers
Classifier: Intended Audience :: System Administrators
Classifier: Operating System :: OS Independent
Classifier: Topic :: Software Development
License-File: LICENSE
Requires-Dist: jinja2
Provides-Extra: yaml
Requires-Dist: jinja2; extra == "yaml"
Requires-Dist: pyyaml; extra == "yaml"
Provides-Extra: toml
Requires-Dist: jinja2; extra == "toml"
Requires-Dist: tomli; python_version < "3.11" and extra == "toml"
Provides-Extra: xml
Requires-Dist: jinja2; extra == "xml"
Requires-Dist: xmltodict; extra == "xml"
Provides-Extra: tests
Requires-Dist: jinja2; extra == "tests"
Requires-Dist: pytest; extra == "tests"
Requires-Dist: flake8; extra == "tests"
Provides-Extra: hjson
Requires-Dist: jinja2; extra == "hjson"
Requires-Dist: hjson; extra == "hjson"
Provides-Extra: json5
Requires-Dist: jinja2; extra == "json5"
Requires-Dist: json5; extra == "json5"
Dynamic: author
Dynamic: author-email
Dynamic: classifier
Dynamic: description
Dynamic: home-page
Dynamic: license
Dynamic: license-file
Dynamic: provides-extra
Dynamic: requires-dist
Dynamic: summary
